lib2toast/__init__.py
lib2toast/__main__.py
lib2toast/api.py
lib2toast/compile.py
lib2toast/debug.py
lib2toast/py.typed
lib2toast/unicode_fix.py
lib2toast-0.1.0.dist-info/METADATA
lib2toast-0.1.0.dist-info/WHEEL
lib2toast-0.1.0.dist-info/licenses/LICENSE
lib2toast-0.1.0.dist-info/RECORD
