Metadata-Version: 2.3
Name: lib2toast
Version: 0.1.0
Summary: Compiling a lib2to3 CST to a Python AST
Author-email: Jelle Zijlstra <jelle.zijlstra@gmail.com>
License-File: LICENSE
Classifier: License :: OSI Approved :: MIT License
Classifier: Operating System :: OS Independent
Classifier: Programming Language :: Python :: 3
Requires-Python: >=3.9
Requires-Dist: black
Requires-Dist: typing-extensions
